{
  "content": "that the password expired. Reset the password by entering the new password twice. Separate the passwords with a forward slash (/). You see resource errors, which are expected: LOGON IBMUSER RPIMGR042I PASSWORD EXPIRED To change your password - enter: nnn/nnn where nnn = new password or, enter LOGOFF to cancel ICH70001I IBMUSER LAST ACCESS AT **:**:** ON ****, **** **,**** HCPRPW004I Password changed RPIMGR031E RESOURCE MAINT.190 SPECIFIED BY LINK COMMAND NOT FOUND RPIMGR031E RESOURCE MAINT.19E SPECIFIED BY LINK COMMAND NOT FOUND RPIMGR031E RESOURCE 7VMRAC20.29E SPECIFIED BY LINK COMMAND NOT FOUND RPIMGR031E RESOURCE 7VMRAC20.505 SPECIFIED BY LINK COMMAND NOT FOUND RPIMGR031E RESOURCE 7VMRAC20.191 SPECIFIED BY LINK COMMAND NOT FOUND RPIMGR031E RESOURCE RACFVM.305 SPECIFIED BY LINK COMMAND NOT FOUND RPIMGR031E RESOURCE IBMUSER.191 SPECIFIED BY LINK COMMAND NOT FOUND z/VM Version 7 Release 2.0, Service Level 2001 (64-bit), built on IBM Virtualization Technology There is no logmsg data",
  "metadata": {
    "title": "Virtualization Cookbook for IBM Z Volume 1: IBM z/VM 7.2",
    "author": "IBM",
    "date": "D:20241111075020Z",
    "abstract": null,
    "keywords": [
      "S/390 Satellite System z Tivoli VTAM WebSphere XIV z Systems z/Architecture z/OS z/VM z/VSE z13 z15 zEnterprise Linux ITIL Windows Microsoft Java Red Hat OpenShift Fedora Ansible UNIX VMware AIX DB2 DS8000 eServer FICON FlashCopy"
    ],
    "file_name": "sg248147.pdf",
    "file_size": 6234969,
    "page_count": 546,
    "processed_date": "2025-03-17T13:37:11.729188",
    "chunk_number": 391,
    "word_count": 145
  }
}